archytas/__init__.py
archytas/agent.py
archytas/archytypes.py
archytas/chat_history.py
archytas/constants.py
archytas/demo_tools.py
archytas/exceptions.py
archytas/mcp_tools.py
archytas/message_schemas.py
archytas/models/__init__.py
archytas/models/anthropic.py
archytas/models/azure.py
archytas/models/base.py
archytas/models/bedrock.py
archytas/models/gemini.py
archytas/models/groq.py
archytas/models/ollama.py
archytas/models/openai.py
archytas/models/openrouter.py
archytas/prompt.py
archytas/prompts/summarization/default_history_summarization_system.jinja
archytas/prompts/summarization/default_history_summarization_user.jinja
archytas/python.py
archytas/react.py
archytas/repl.py
archytas/structured_data_utils.py
archytas/summarizers.py
archytas/tool_utils.py
archytas/tools.py
archytas/utils.py
archytas-1.6.6.dist-info/METADATA
archytas-1.6.6.dist-info/WHEEL
archytas-1.6.6.dist-info/entry_points.txt
archytas-1.6.6.dist-info/licenses/LICENSE
archytas-1.6.6.dist-info/RECORD
