Metadata-Version: 2.4
Name: archytas
Version: 1.6.6
Summary: A library for pairing LLM agents with tools so they perform open ended tasks
License: GPL-3.0-or-later
License-File: LICENSE
Author: David Andrew Samson
Author-email: david.andrew.engineer@gmail.com
Requires-Python: >=3.10
Classifier: License :: OSI Approved :: GNU General Public License v3 or later (GPLv3+)
Classifier: Programming Language :: Python :: 3
Classifier: Programming Language :: Python :: 3.10
Classifier: Programming Language :: Python :: 3.11
Classifier: Programming Language :: Python :: 3.12
Classifier: Programming Language :: Python :: 3.13
Classifier: Programming Language :: Python :: 3.14
Provides-Extra: dev
Provides-Extra: testing
Requires-Dist: anthropic (>=0.70)
Requires-Dist: azure-ai-inference (>=1.0.0b9)
Requires-Dist: botocore (>=1.37)
Requires-Dist: docstring-parser (>=0.16)
Requires-Dist: easyrepl (>=0.1.2) ; extra == "dev"
Requires-Dist: fastmcp (>=0.1.0) ; extra == "testing"
Requires-Dist: frozendict (>=2.3.8)
Requires-Dist: jinja2 (>=3.1.6)
Requires-Dist: langchain (>=1.0)
Requires-Dist: langchain-anthropic (>=1.0)
Requires-Dist: langchain-aws (>=1.0)
Requires-Dist: langchain-community (>=0.4)
Requires-Dist: langchain-core (>=1.0)
Requires-Dist: langchain-google-genai (>=2.1)
Requires-Dist: langchain-groq (>=1.0)
Requires-Dist: langchain-mcp-adapters (>=0.1.0)
Requires-Dist: langchain-ollama (>=1.0)
Requires-Dist: langchain-openai (>=1.0)
Requires-Dist: openai (>=2.0)
Requires-Dist: pydantic (>=1.9.0)
Requires-Dist: pytest (>=8.4.2) ; extra == "dev"
Requires-Dist: pytest (>=8.4.2) ; extra == "testing"
Requires-Dist: pytest-asyncio ; extra == "dev"
Requires-Dist: pytest-asyncio ; extra == "testing"
Requires-Dist: pytest-xdist ; extra == "dev"
Requires-Dist: pytest-xdist ; extra == "testing"
Requires-Dist: pytz (>=2023.3)
Requires-Dist: rich (>=13.3.4)
Requires-Dist: toki (>=0.2.8)
Requires-Dist: toml (>=0.10.2)
Project-URL: Bug Tracker, https://github.com/jataware/archytas/issues
Project-URL: Homepage, https://github.com/jataware/archytas
